ambition_validators/__init__.py
ambition_validators/apps.py
ambition_validators/constants.py
ambition_validators/models.py
ambition_validators/settings.py
ambition_validators/urls.py
ambition_validators/wsgi.py
ambition_validators/form_validators/__init__.py
ambition_validators/form_validators/amphotericin_missed_doses.py
ambition_validators/form_validators/blood_result.py
ambition_validators/form_validators/education.py
ambition_validators/form_validators/fluconazole_missed_doses.py
ambition_validators/form_validators/flucytosine_missed_doses.py
ambition_validators/form_validators/follow_up.py
ambition_validators/form_validators/lumbar_puncture_csf.py
ambition_validators/form_validators/medical_expenses.py
ambition_validators/form_validators/medical_expenses_two_detail.py
ambition_validators/form_validators/microbiology.py
ambition_validators/form_validators/missed_doses.py
ambition_validators/form_validators/patient_history.py
ambition_validators/form_validators/pk_pd_crf.py
ambition_validators/form_validators/previous_opportunistic_infection.py
ambition_validators/form_validators/radiology.py
ambition_validators/form_validators/significant_diagnoses.py
ambition_validators/form_validators/subject_consent.py
ambition_validators/form_validators/subject_screening.py
ambition_validators/form_validators/week16.py
ambition_validators/form_validators/week2.py
ambition_validators/form_validators/week4.py
ambition_validators/tests/__init__.py
ambition_validators/tests/models.py
ambition_validators/tests/test_blood_result_form_validator.py
ambition_validators/tests/test_education_validator.py
ambition_validators/tests/test_follow_up_form_validator.py
ambition_validators/tests/test_lumbar_puncture_form_validator.py
ambition_validators/tests/test_medical_expenses_form_validator.py
ambition_validators/tests/test_medical_expenses_two_form_validator.py
ambition_validators/tests/test_microbiology_form_validator.py
ambition_validators-0.1.10.dist-info/METADATA
ambition_validators-0.1.10.dist-info/RECORD
ambition_validators-0.1.10.dist-info/WHEEL
ambition_validators-0.1.10.dist-info/top_level.txt
