Metadata-Version: 2.1
Name: ambition-validators
Version: 0.1.10
Summary: Validators for ambition/edc project
Home-page: https://github.com/ambition-trial/ambition-validators
Author: Erik van Widenfelt
Author-email: ew2789@gmail.com
License: GPL license, see LICENSE
Keywords: django ambition
Platform: UNKNOWN
Classifier: Environment :: Web Environment
Classifier: Framework :: Django
Classifier: Intended Audience :: Developers
Classifier: Intended Audience :: Science/Research
Classifier: License :: OSI Approved :: GNU General Public License v3 (GPLv3)
Classifier: Operating System :: OS Independent
Classifier: Programming Language :: Python :: 3.6
Classifier: Programming Language :: Python :: 3.7
Classifier: Topic :: Internet :: WWW/HTTP
Classifier: Topic :: Internet :: WWW/HTTP :: Dynamic Content
Requires-Dist: ambition-screening
Requires-Dist: ambition-labs
Requires-Dist: ambition-prn
Requires-Dist: ambition-sites
Requires-Dist: ambition-subject
Requires-Dist: ambition-visit-schedule
Requires-Dist: edc-appointment
Requires-Dist: edc-base
Requires-Dist: edc-constants
Requires-Dist: edc-form-validators
Requires-Dist: edc-lab
Requires-Dist: edc-reportable
